{
  "ret_code": 1,
  "ret_data":
  {
    "residentName": "李晋辩",
    "residentNo": "44030500100103309",
    "bodySymptomDes": "",
    "bodySymptomList": [
    {
      "sympId": 10030,
      "docType": 30,
      "docId": 135,
      "userId": 6000009881,
      "symName": "sym_headache",
      "symType": 0,
      "symDescribe": ""
    },
    {
      "sympId": 10031,
      "docType": 30,
      "docId": 135,
      "userId": 6000009881,
      "symName": "sym_dizzy",
      "symType": 0,
      "symDescribe": ""
    },
    {
      "sympId": 10032,
      "docType": 30,
      "docId": 135,
      "userId": 6000009881,
      "symName": "sym_palpitation",
      "symType": 0,
      "symDescribe": ""
    },
    {
      "sympId": 10033,
      "docType": 30,
      "docId": 135,
      "userId": 6000009881,
      "symName": "sym_chest_tightness",
      "symType": 0,
      "symDescribe": ""
    },
    {
      "sympId": 10034,
      "docType": 30,
      "docId": 135,
      "userId": 6000009881,
      "symName": "sym_chest_pain_only",
      "symType": 0,
      "symDescribe": ""
    },
    {
      "sympId": 10035,
      "docType": 30,
      "docId": 135,
      "userId": 6000009881,
      "symName": "sym_chronic_cough",
      "symType": 0,
      "symDescribe": ""
    },
    {
      "sympId": 10036,
      "docType": 30,
      "docId": 135,
      "userId": 6000009881,
      "symName": "sym_expectoration",
      "symType": 0,
      "symDescribe": ""
    },
    {
      "sympId": 10037,
      "docType": 30,
      "docId": 135,
      "userId": 6000009881,
      "symName": "sym_dyspnea",
      "symType": 0,
      "symDescribe": ""
    },
    {
      "sympId": 10038,
      "docType": 30,
      "docId": 135,
      "userId": 6000009881,
      "symName": "sym_drink_more",
      "symType": 0,
      "symDescribe": ""
    },
    {
      "sympId": 10039,
      "docType": 30,
      "docId": 135,
      "userId": 6000009881,
      "symName": "sym_polyuria",
      "symType": 0,
      "symDescribe": ""
    },
    {
      "sympId": 10040,
      "docType": 30,
      "docId": 135,
      "userId": 6000009881,
      "symName": "sym_weight_loss",
      "symType": 0,
      "symDescribe": ""
    },
    {
      "sympId": 10041,
      "docType": 30,
      "docId": 135,
      "userId": 6000009881,
      "symName": "sym_weak",
      "symType": 0,
      "symDescribe": ""
    },
    {
      "sympId": 10042,
      "docType": 30,
      "docId": 135,
      "userId": 6000009881,
      "symName": "sym_joint_swelling",
      "symType": 0,
      "symDescribe": ""
    },
    {
      "sympId": 10043,
      "docType": 30,
      "docId": 135,
      "userId": 6000009881,
      "symName": "sym_blurred_vision",
      "symType": 0,
      "symDescribe": ""
    },
    {
      "sympId": 10044,
      "docType": 30,
      "docId": 135,
      "userId": 6000009881,
      "symName": "sym_motion",
      "symType": 0,
      "symDescribe": ""
    },
    {
      "sympId": 10045,
      "docType": 30,
      "docId": 135,
      "userId": 6000009881,
      "symName": "sym_urgency",
      "symType": 0,
      "symDescribe": ""
    },
    {
      "sympId": 10046,
      "docType": 30,
      "docId": 135,
      "userId": 6000009881,
      "symName": "sym_odynuria",
      "symType": 0,
      "symDescribe": ""
    },
    {
      "sympId": 10047,
      "docType": 30,
      "docId": 135,
      "userId": 6000009881,
      "symName": "sym_constipation",
      "symType": 0,
      "symDescribe": ""
    },
    {
      "sympId": 10048,
      "docType": 30,
      "docId": 135,
      "userId": 6000009881,
      "symName": "sym_diarrhea",
      "symType": 0,
      "symDescribe": ""
    },
    {
      "sympId": 10049,
      "docType": 30,
      "docId": 135,
      "userId": 6000009881,
      "symName": "sym_NV",
      "symType": 0,
      "symDescribe": ""
    },
    {
      "sympId": 10050,
      "docType": 30,
      "docId": 135,
      "userId": 6000009881,
      "symName": "sym_vertigo",
      "symType": 0,
      "symDescribe": ""
    },
    {
      "sympId": 10051,
      "docType": 30,
      "docId": 135,
      "userId": 6000009881,
      "symName": "sym_tinnitus",
      "symType": 0,
      "symDescribe": ""
    },
    {
      "sympId": 10052,
      "docType": 30,
      "docId": 135,
      "userId": 6000009881,
      "symName": "sym_breast_tenderness",
      "symType": 0,
      "symDescribe": ""
    },
    {
      "sympId": 10053,
      "docType": 30,
      "docId": 135,
      "userId": 6000009881,
      "symName": "sym_other",
      "symType": 1,
      "symDescribe": ""
    }],
    "riskFactor":
    {
      "rfcId": 135,
      "docType": 30,
      "docId": 135,
      "userId": 6000009881,
      "examId": 0,
      "rfcNoSmoking": 1,
      "rfcHealthyDrinking": 1,
      "rfcFood": 1,
      "rfcExercise": 1,
      "rfcReduceWeight": 1,
      "rfcRwTarget": 50,
      "rfcVaccination": 1,
      "rfcVaccineName": "流感疫苗",
      "rfcOther": 1,
      "rfcOtherDescribe": "保健"
    },
    "riskFactorDes": "",
    "eatHabits":
    {
      "eatId": 135,
      "docType": 30,
      "docId": 135,
      "userId": 6000009881,
      "eatMeatVegetables": 1,
      "eatMeatMain": "",
      "eatVegetables": "",
      "eatHalophilic": 0,
      "eatOil": 0,
      "eatSugar": 1,
      "eatDescribe": ""
    },
    "eatHabitsDes": "荤素均衡、嗜糖",
    "careerDisease":
    {
      "careerId": 135,
      "userId": 6000009881,
      "docType": 30,
      "docId": 135,
      "careerFlag": 1,
      "careerName": "",
      "careerTime": 0,
      "careerDustName": "",
      "careerDustProtectFlag": 0,
      "careerDustProtectMeasures": "",
      "careerRadiationName": "",
      "careerRadiationProtectFlag": 0,
      "careerRadiationProtectMeasures": "",
      "careerPhysicsName": "",
      "careerPhysicsProtectFlag": 0,
      "careerPhysicsProtectMeasures": "",
      "careerChemistryName": "",
      "careerChemistryProtect": 0,
      "careerChemistryProtectMeasures": "",
      "careerOtherName": "",
      "careerOtherProtectFlag": 0,
      "careerOtherProtectMeasures": "",
      "protectMeasures": []
    },
    "gynaecology":
    {
      "gynaId": 271,
      "userId": 6000009881,
      "docType": 30,
      "docId": 135,
      "examDate": "",
      "gynaVulva": 2,
      "gynaVulvaExce": "",
      "gynaVulvadDes": "未见异常",
      "gynaVagina": 2,
      "gyanVaginaExce": "",
      "gynaVaginaDes": "未见异常",
      "gynaCervical": 2,
      "gynaCervicalExce": "",
      "gynaCervicalDes": "未见异常",
      "gynaPalace": 2,
      "gynaPalaceExce": "",
      "gynaPalaceDes": "未见异常",
      "gynaEnclosure": 2,
      "gynaEnclosureExce": "",
      "gynaEnclosureDes": "未见异常"
    },
    "tcmConstitution": "",
    "cerebroDisease":
    {
      "tconId": 135,
      "docType": 30,
      "docId": 135,
      "userId": 6000009881,
      "tconFlag": 1,
      "tconIschemicStroke": 1,
      "tconCerebralHemorrhage": 1,
      "tconSubarchnoidHemorrhage": 1,
      "tconTransientCerebral": 1,
      "tconOther": 1,
      "tconOtherDisease": "无",
      "tconDate": ""
    },
    "cerebroDiseaseDes": "缺血性卒中、脑出血、蛛网膜下腔出血、短暂性脑缺血、无",
    "kidneyDisease":
    {
      "kidnId": 135,
      "docType": 30,
      "docId": 135,
      "userId": 6000009881,
      "kidnFlag": 2,
      "kidnDiabets": 0,
      "kidnRenalFailure": 0,
      "kidnAcuteNephritis": 0,
      "kidnChronicNephritis": 0,
      "kidnOther": 0,
      "kidnOtherDescribe": ""
    },
    "kidneyDiseaseDes": "未发现",
    "heartDisease":
    {
      "heartId": 135,
      "userId": 6000009881,
      "docType": 30,
      "docId": 135,
      "heartFlag": 2,
      "heartMiocardialInfartion": 0,
      "heartAnginaPectoris": 0,
      "heartCoronaryReva": 0,
      "heartCongestiveFail": 0,
      "heartPrecordialPain": 0,
      "heartOther": 0,
      "heartOtherDescribe": ""
    },
    "heartDiseaseDes": "未发现",
    "vascularDisease":
    {
      "vascId": 135,
      "userId": 6000009881,
      "docType": 30,
      "docId": 135,
      "vascFlag": 2,
      "vascDissectingAneurysm": 0,
      "vascArterialOcclusive": 0,
      "vascOther": 0,
      "vascOtherDescribe": ""
    },
    "vascularDiseaseDes": "未发现",
    "eyeDisease":
    {
      "eyeId": 135,
      "userId": 6000009881,
      "docType": 30,
      "docId": 135,
      "eyeFlag": 2,
      "eyeRetinalException": 0,
      "eyePapillaryEdema": 0,
      "eyeCataract": 0,
      "eyeOther": 0,
      "eyeOtherDescribe": ""
    },
    "eyeDiseaseDes": "未发现",
    "breast":
    {
      "breastId": 135,
      "userId": 6000009881,
      "docType": 30,
      "docId": 135,
      "exceFlag": 1,
      "exceNo": "",
      "exceCut": "",
      "exceLactation": "",
      "exceMass": "",
      "exceOtherFlag": "",
      "exceOtherDescribe": ""
    },
    "breastDes": "未见异常",
    "examId": 135,
    "actId": 0,
    "userId": 6000009881,
    "examDoctor": "",
    "examDate": 0,
    "examSymptom": 2,
    "examTemperature": 38,
    "examPulseRate": 63,
    "examBreathingRate": 62,
    "examLeftBloodLow": 95,
    "examLeftBloodHigh": 82,
    "examRightBloodLow": 82,
    "examRightBloodHigh": 71,
    "examHeight": 165,
    "examWeight": 65,
    "examWaist": 123,
    "examBmi": 23.88,
    "examSelfCare": 1,
    "examSelfCareDes": "可自理（0～3分）",
    "examHealthStatus": 1,
    "examHealthStatusDes": "满意",
    "elderCognitiveAbility": 1,
    "elderCognitiveScore": 0,
    "elderCognitiveDes": "粗筛阴性",
    "elderEmotionStatus": 1,
    "elderEmotionScore": 0,
    "elderEmotionDes": "粗筛阴性",
    "examExerciseFrequency": 4,
    "examExerciseFrequencyDes": "不锻炼",
    "examExerciseTime": 0,
    "examExerciseTotal": 0,
    "examExerciseType": "",
    "examSmokingStatus": 1,
    "smokingStateDes": "从不吸烟",
    "examSmokingQuantity": 0,
    "examSmokingBegin": 0,
    "examSmokingCessation": 0,
    "examDrinkingFrequency": 1,
    "examDailyDrinking": 0,
    "examDrinkingCessation": 0,
    "examDrinkCessationAge": 0,
    "examDrinkingAge": 0,
    "examLastDrunk": 0,
    "examLastDrunkDes": "否",
    "examSpirit": 0,
    "examBeer": 0,
    "examRedwine": 0,
    "examYellowwine": 0,
    "examDrinkingType": 0,
    "examWineOther": "",
    "examLips": 1,
    "examLipsDes": "红润",
    "examDentitionStatus": 1,
    "examMissingTeeth": 0,
    "examMissingteethLeftupper": 0,
    "examMissingteethRightupper": 0,
    "examMissingteethLeftlower": 0,
    "examMissingteethRightlower": 0,
    "examDentalTeeth": 0,
    "examDentalLeftupper": 0,
    "examDentalRightupper": 0,
    "examDentalLeftlower": 0,
    "examDentalRightlower": 0,
    "examFalseTeeth": 0,
    "examFalseLeftupper": 0,
    "examFalseRightupper": 0,
    "examFalseLeftlower": 0,
    "examFalseRightlower": 0,
    "teethDes": "正常",
    "examPharynx": 1,
    "pharynxDes": "无充血",
    "examVisionLeft": 15,
    "examVisionRight": 15,
    "examCorrectVisionLeft": 2,
    "examCorrectVisionRight": 3,
    "examHearing": 1,
    "examHearingDes": "听见",
    "examExerciseAbility": 1,
    "examExerciseAbilityDes": "可顺利完成",
    "examFundusOculi": 1,
    "examFundusOculiException": "",
    "examFundusOculiDes": "正常",
    "examSkin": 1,
    "examSkinDes": "正常",
    "examSkinOther": "",
    "examSclera": 1,
    "examScleraOther": "",
    "examScleraDes": "正常",
    "examLymphGland": 1,
    "examLymphGlandOther": "",
    "examLymphGlandDes": "未触及",
    "examBarrelChest": 2,
    "examBarrelChestDes": "否",
    "examBreathSounds": 1,
    "examBreathSoundsOther": "",
    "examBreathSoundsDes": "正常",
    "examRale": 1,
    "examRaleDescribe": "",
    "examRaleDes": "无",
    "examHeartRate": 62,
    "examRhythm": 1,
    "examRhythmDes": "齐",
    "examNoise": 2,
    "examNoiseDescribe": "",
    "examNoiseDes": "无",
    "examTenderness": 2,
    "examTendernessDescribe": "",
    "examTendernessDes": "无",
    "examBagPiece": 2,
    "examBagPieceDescribe": "",
    "examBagPieceDes": "无",
    "examLiver": 2,
    "examLiverDescribe": "",
    "examLiverDes": "无",
    "examSplenomegaly": 2,
    "examSplenomegalyDescribe": "",
    "examSplenomegalyDes": "无",
    "examMobileDullness": 2,
    "examMobileDullnessDescribe": "",
    "examMobileDullnessDes": "无",
    "examEdemaLower": 1,
    "examEdemaLowerDes": "无",
    "examDorsalisPedis": 1,
    "dorsalisPedisDes": "未触及",
    "examDra": 1,
    "examDraDescribe": "",
    "examDraDes": "未及异常",
    "examBreast": "",
    "examBodyChecking": "无",
    "examAuxiliaryBloodHemoglobin": 99,
    "examAuxiliaryBloodWhitecell": 9,
    "examAuxiliaryBloodPlatelet": 99,
    "examAuxiliaryBloodOther": "无其他",
    "examAuxiliaryUrineProtein": "99",
    "examAuxiliaryUrineKetone": "99",
    "examAuxiliaryUrineBld": "99",
    "examAuxiliaryUrineSugar": "99",
    "examAuxiliaryUrineOther": "99",
    "examAuxiliaryBloodGlucose1": 9,
    "examAuxiliaryBloodGlucose2": "",
    "examAuxiliaryCardiogram": 2,
    "examAuxiliaryCardiogramDes": "正常",
    "examAuxiliaryCardiogramExce": "",
    "examAuxiliaryUrineMicroalbumin": 99,
    "examAuxiliaryOccultBlood": 1,
    "examAuxiliaryOccultBloodDes": "阴性",
    "examAuxiliaryGlycosylatedHemoglobin": 99,
    "examAuxiliarySurfaceAntigen": 1,
    "examAuxiliarySurfaceAntigendDes": "阴性",
    "examAuxiliaryLiverSgpt": 99,
    "examAuxiliaryLiverSgot": 99,
    "examAuxiliaryLiverAlbumin": 99,
    "examAuxiliaryLiverBilirubin": 9,
    "examAuxiliaryLiverConjugated": 99,
    "examAuxiliaryKidneyScr": 99,
    "examAuxiliaryKidneyNitrogen": 9,
    "examAuxiliaryKidneyPotassium": 9,
    "examAuxiliaryKidneySodium": 99,
    "examAuxiliaryLipidCholesterol": 99,
    "examAuxiliaryLipidLipoprotein": 99,
    "examAuxiliaryLipidTriglyceride": 9,
    "examAuxiliaryLipidHigh": 9,
    "examAuxiliaryChestradiograph": 2,
    "examAuxiliaryChestradiographExce": "",
    "examAuxiliaryChestradiographDes": "正常",
    "examAuxiliaryAbdominalUltrasonography": 2,
    "examAuxiliaryAbdominalExce": "",
    "examAuxiliaryAbdominalExceDes": "正常",
    "examAuxiliaryAbdominalOther": 2,
    "examAuxiliaryAbdominalOtherdexce": "",
    "examAuxiliaryAbdominalOtherDes": "正常",
    "examAuxiliaryUltrasonographyDes": "",
    "examAuxiliaryCervicalSmear": "2",
    "examAuxiliaryCervicalExce": "",
    "examAuxiliaryCervicalSmearDes": "正常",
    "examAuxiliaryOther": "99",
    "pdhNervousDisease": 2,
    "pdhNervousDiseaseExce": "",
    "pdhNervousDiseaseDes": "未发现",
    "pdhOtherDiseases": 2,
    "pdhOtherDiseasesExce": "",
    "pdhOtherDiseasesDes": "未发现",
    "healthAssessment": 1,
    "healthNovaccinationName": "预防针",
    "healthNovaccinationDate": 1502985600000,
    "healthNovaccinationOrg": "卫生站",
    "healthAsseException1": "高血压",
    "healthAsseException2": "哮喘",
    "healthAsseException3": "",
    "healthAsseException4": "",
    "healthAssessmentDes": "高血压;哮喘",
    "healthGuidanceManager": 1,
    "healthGuidanceReview": 1,
    "healthGuidanceReferral": 1,
    "healthGuideDes": "患者健康管理、建议复查、建议转诊",
    "examBedIn": 1502985600000,
    "examBedOut": 1502985600000,
    "examBedReason": "高血压",
    "examBedOrg": "三院",
    "examBedNo": "002",
    "examHospitalIn": 1502985600000,
    "examHospitalOut": 1502985600000,
    "examHospitalName": "三院",
    "examHospitalReason": "高血压",
    "examHospitalNo": "003",
    "examDrugName": "阿司匹林",
    "examDrugUse": "口服",
    "examDrugDosage": "一日一次",
    "examDrugDate": 1502985600000,
    "examDrugDependence": 3,
    "examDrugDependenceDes": "不服药",
    "examRiskFactor": "",
    "impactDataUrl": "",
    "createBy": 5000001015,
    "createDate": 1503044510545,
    "updateBy": "",
    "updateDate": 1503044510545,
    "attribute1": "",
    "attribute2": "",
    "attribute3": "",
    "attribute4": "",
    "attribute5": "",
    "attribute6": "",
    "attribute7": "",
    "attribute8": "",
    "attribute9": "",
    "attribute10": "",
    "examinationExtend":
    {
      "residentName": "",
      "residentNo": "",
      "extendId": "",
      "userId": "",
      "internalPastHistory": "",
      "internalAuscultation": "",
      "internalHeartRate": "",
      "internalRhythm": "",
      "internalHeartSounds": "",
      "internalNoise": "",
      "internalAbdominalTouch": "",
      "internalNervousSystem": "",
      "internalOther": "",
      "surgeryPastHistory": "",
      "surgerySkin": "",
      "surgeryIymphNode": "",
      "surgeryThyroid": "",
      "surgerySpinalLimbs": "",
      "surgeryGenitals": "",
      "surgeryAnus": "",
      "surgeryOther": "",
      "eyePastHistory": "",
      "eyeNvRight": "",
      "eyeNvLeft": "",
      "eyeJzRight": "",
      "eyeJzLeft": "",
      "eyeColorBlindness": "",
      "eyeLid": "",
      "eyeApparatusLacrimalis": "",
      "eyeConjunctiva": "",
      "eyeSclera": "",
      "eyeBall": "",
      "eyeOther": "",
      "dentalPastHistory": "",
      "dentalPeriodontium": "",
      "dentalEndodontics": "",
      "dentalMalocclusion": "",
      "dentalLip": "",
      "dentalTongue": "",
      "dentalMaxillofacialRegion": "",
      "dentalOther": "",
      "entPastHistory": "",
      "entListen": "",
      "entAurisExterna": "",
      "entAcousticDuct": "",
      "entDrum": "",
      "entNasusExternus": "",
      "entNasalCavity": "",
      "entPartesOralis": "",
      "entOther": "",
      "electrolyticK": "",
      "electrolyticNa": "",
      "electrolyticCl": "",
      "electrolyticPh": "",
      "electrolyticNca": "",
      "electrolyticTca": "",
      "electrolyticIca": "",
      "electrolyticLi": "",
      "twoliverAlt": "",
      "twoliverAst": "",
      "threekidneyUa": "",
      "threekidneyUrea": "",
      "threekidneyCr": "",
      "routineBloodWbc": "",
      "routineBloodLymphc": "",
      "routineBloodBasoc": "",
      "routineBloodMonoc": "",
      "routineBloodNeutc": "",
      "routineBloodEoc": "",
      "routineBloodLymphr": "",
      "routineBloodBasor": "",
      "routineBloodMonor": "",
      "routineBloodNeutr": "",
      "routineEor": "",
      "routineRbc": "",
      "routineHgb": "",
      "routineHct": "",
      "routineMcv": "",
      "routineMch": "",
      "routineMchc": "",
      "routineSd": "",
      "routineCv": "",
      "routinePlt": "",
      "routinePdw": "",
      "routineMpv": "",
      "routinePLcr": "",
      "routinePct": "",
      "routineLymc": "",
      "routineMidc": "",
      "routineGrnc": "",
      "routineLymr": "",
      "routineMidr": "",
      "routineGrnr": "",
      "routineOthrc": "",
      "routineOthrr": "",
      "bhepatitisHbsag": "",
      "bhepatitisHbsab": "",
      "bhepatitisHbeag": "",
      "bhepatitisHbeab": "",
      "bhepatitisHbcab": "",
      "threetumorCea": "",
      "threetumorAfp": "",
      "threetumorEbVcaiga": "",
      "urinalysisPro": "",
      "urinalysisGlu": "",
      "urinalysisPh": "",
      "urinalysisKet": "",
      "urinalysisBil": "",
      "urinalysisUro": "",
      "urinalysisBld": "",
      "urinalysisNit": "",
      "urinalysisLeu": "",
      "urinalysisSg": "",
      "urinalysisVc": "",
      "urinalysisCre": "",
      "urinalysisCa": "",
      "urinalysisMa": "",
      "biochemistryGgt": "",
      "biochemistryCrep": "",
      "biochemistryTbil": "",
      "biochemistryUrea": "",
      "biochemistryAlt": "",
      "biochemistryDbil": "",
      "biochemistryHdlc": "",
      "biochemistryLdlc": "",
      "biochemistryAst": "",
      "biochemistryTg": "",
      "biochemistryTp": "",
      "biochemistryAlb": "",
      "biochemistryCho": "",
      "biochemistryGlu": "",
      "biochemistryChe": "",
      "biochemistryTba": "",
      "biochemistryCres": "",
      "biochemistryUa": "",
      "biochemistryCysc": "",
      "biochemistryLdh": "",
      "biochemistryIgg": "",
      "biochemistryCk": "",
      "biochemistryCkmb": "",
      "biochemistryAso": "",
      "biochemistryApoa1": "",
      "biochemistryAopb": "",
      "biochemistryAmy": "",
      "biochemistryCa": "",
      "biochemistryMg": "",
      "biochemistryCo2": "",
      "biochemistryIp": "",
      "biochemistryRf": "",
      "biochemistryPa": "",
      "biochemistryAda": "",
      "poctcrpPct": "",
      "poctcrpCrp": "",
      "poctcrpMalb": "",
      "poctcrpSf": "",
      "poctcrpTsh": "",
      "poctcrpHcg": "",
      "poctcrpLh": "",
      "poctcrpFsh": "",
      "poctcrpHiv12": "",
      "poctcrpHcv": "",
      "poctcrpTb": "",
      "poctcrpHbsag": "",
      "poctcrpTp": "",
      "poctcrpHev": "",
      "poctcrpHpab": "",
      "poctcrpHpag": "",
      "poctcrpMor": "",
      "poctcrpMet": "",
      "poctcrpFob": "",
      "poctcrpUrs": "",
      "createBy": "",
      "createDate": "",
      "updateBy": "",
      "updateDate": ""
    },
    "iossDataMap": "",
    "drinkingCessationDes": "未戒酒",
    "drinkingTypeDes": "无"
  }
}